mine.py
mcpi/__init__.py
mcpi/block.py
mcpi/connection.py
mcpi/entity.py
mcpi/event.py
mcpi/minecraft.py
mcpi/nbt.py
mcpi/security-template.py
mcpi/settings.py
mcpi/util.py
mcpi/vec3.py
mcpi/vpython_minecraft.py
raspberryjammod/VERSION
raspberryjammod/__init__.py
raspberryjammod/__main__.py
raspberryjammod-0.92.1.dist-info/DESCRIPTION.rst
raspberryjammod-0.92.1.dist-info/METADATA
raspberryjammod-0.92.1.dist-info/RECORD
raspberryjammod-0.92.1.dist-info/WHEEL
raspberryjammod-0.92.1.dist-info/metadata.json
raspberryjammod-0.92.1.dist-info/top_level.txt
